CHANGELOG.txt
LICENCE.txt
MANIFEST.in
README.txt
setup.py
sapiva/__init__.py
sapiva.egg-info/PKG-INFO
sapiva.egg-info/SOURCES.txt
sapiva.egg-info/dependency_links.txt
sapiva.egg-info/top_level.txt