Metadata-Version: 1.1
Name: sapiva
Version: 0.0.1
Summary: Sapi makes creating virtual assitence very simple
Home-page: UNKNOWN
Author: Parteek Deol
Author-email: 610078787@musd.net
License: MIT
Keywords: robot
Platform: UNKNOWN
Classifier: Development Status :: 5 - Production/Stable
Classifier: Intended Audience :: Education
Classifier: Operating System :: Microsoft :: Windows :: Windows 10
Classifier: License :: OSI Approved :: MIT License
Classifier: Programming Language :: Python :: 3
